puppetry/__about__.py
puppetry/__init__.py
puppetry/__main__.py
puppetry/client.py
puppetry/server.py
puppetry/tests/__init__.py
puppetry/tests/test_echo_class.py
puppetry-0.0.1.dist-info/LICENSE
puppetry-0.0.1.dist-info/METADATA
puppetry-0.0.1.dist-info/WHEEL
puppetry-0.0.1.dist-info/top_level.txt
puppetry-0.0.1.dist-info/RECORD
