Metadata-Version: 2.1
Name: puppetry
Version: 0.0.1
Summary: puppetry with objects
Home-page: https://github.com/axju/puppetry
Author: Axel Juraske
Author-email: axel.juraske@short-report.de
License: MIT
Keywords: socketserver socket pickle serializer
Platform: UNKNOWN
Classifier: Intended Audience :: Developers
Classifier: Operating System :: OS Independent
Classifier: Programming Language :: Python
Classifier: Programming Language :: Python :: 3.5
Classifier: Programming Language :: Python :: 3.6
Classifier: Programming Language :: Python :: 3.7
